LICENSE
MANIFEST.in
README.md
pyproject.toml
setup.cfg
setup.py
bin/PyAlarm
bin/panic
panic/CHANGES
panic/PyAlarm.ctsaal01.py
panic/VERSION
panic/__init__.py
panic/alarmapi.py
panic/engine.py
panic/properties.py
panic/test.py
panic/view.py
panic/widgets.py
panic.egg-info/PKG-INFO
panic.egg-info/SOURCES.txt
panic.egg-info/dependency_links.txt
panic.egg-info/entry_points.txt
panic.egg-info/requires.txt
panic.egg-info/top_level.txt
panic/ds/PanicViewDS.py
panic/ds/PyAlarm.py
panic/ds/SenderDS.py
panic/ds/__init__.py
panic/ds/__main__.py
panic/ds/kpi.py
panic/extra/__init__.py
panic/extra/http.py
panic/extra/report.py
panic/gui/__init__.py
panic/gui/__main__.py
panic/gui/actions.py
panic/gui/alarmhistory.py
panic/gui/devattrchange.py
panic/gui/editor.py
panic/gui/gui.py
panic/gui/htmlview.py
panic/gui/panel.py
panic/gui/phonebook.py
panic/gui/status.py
panic/gui/toolbar.py
panic/gui/ui_data.py
panic/gui/ui_gui.py
panic/gui/utils.py
panic/gui/views.py
panic/gui/icon/panel-view.png
panic/gui/icon/panic-6-banner.png
panic/gui/icon/panic-6-banner.svg
panic/gui/icon/panic-6-big.png
panic/gui/icon/panic-6.png
panic/gui/icon/panic-6.svg
panic/gui/icon/panic-icon.gif
panic/gui/icon/panic-icon.svg