Metadata-Version: 2.1
Name: panic
Version: 9.5.0
Summary: PANIC, a python Alarm System for TANGO
Home-page: https://gitlab.com/tango-controls/panic
Download-URL: https://github.com/tango-controls/panic
Author: Sergi Rubio
Author-email: srubio@cells.es
Maintainer: Sergi Rubio
Maintainer-email: srubio@cells.es
License: LGPL
Classifier: Programming Language :: Python :: 3
Requires-Python: >=3.9
Provides-Extra: gui
License-File: LICENSE
